disk_numpy_array/__init__.py
disk_numpy_array/version.py
disk_numpy_array/disk_numpy_array/__init__.py
disk_numpy_array/disk_numpy_array/disk_numpy_array.py
disk_numpy_array/disk_numpy_array/disk_numpy_array_iterable.py
disk_numpy_array/disk_numpy_array/disk_numpy_array_sequence.py
disk_numpy_array/replacement_strategy/__init__.py
disk_numpy_array/replacement_strategy/replacement_strategy.py
disk_numpy_array/replacement_strategy/sample_num_replacement_strategy.py
disk_numpy_array/utils/__init__.py
disk_numpy_array/utils/save.py
disk_numpy_array-0.1.2.dist-info/LICENSE
disk_numpy_array-0.1.2.dist-info/METADATA
disk_numpy_array-0.1.2.dist-info/WHEEL
disk_numpy_array-0.1.2.dist-info/top_level.txt
disk_numpy_array-0.1.2.dist-info/RECORD
