Metadata-Version: 2.1
Name: disk-numpy-array
Version: 0.1.2
Summary: A library to save and load a large numpy array from disk.
Author-email: shenmishajing <shenmishajing@gmail.com>
License: MIT License
Project-URL: Homepage, https://github.com/shenmishajing/disk_numpy_array
Project-URL: Repository, https://github.com/shenmishajing/disk_numpy_array
Project-URL: Documentation, https://shenmishajing-project-template.readthedocs.io
Project-URL: Issues, https://github.com/shenmishajing/disk_numpy_array/issues
Project-URL: Changelog, https://github.com/shenmishajing/disk_numpy_array/blob/main/docs/get_started/changelog.md
Classifier: Development Status :: 5 - Production/Stable
Classifier: Intended Audience :: Developers
Classifier: License :: OSI Approved :: MIT License
Classifier: Operating System :: OS Independent
Classifier: Environment :: GPU :: NVIDIA CUDA
Classifier: Programming Language :: Python
Classifier: Programming Language :: Python :: 3
Classifier: Programming Language :: Python :: Implementation :: CPython
Classifier: Programming Language :: Python :: Implementation :: PyPy
Classifier: Topic :: Software Development :: Libraries
Classifier: Topic :: Software Development :: Libraries :: Python Modules
Classifier: Natural Language :: Chinese (Simplified)
Requires-Python: >=3.8
License-File: LICENSE
Requires-Dist: numpy
Provides-Extra: all
Requires-Dist: disk-numpy-array[dev] ; extra == 'all'
Provides-Extra: dev
Requires-Dist: disk-numpy-array[dev-build,dev-core,dev-doc,dev-test] ; extra == 'dev'
Provides-Extra: dev-build
Requires-Dist: build ; extra == 'dev-build'
Provides-Extra: dev-commit
Requires-Dist: pre-commit ; extra == 'dev-commit'
Requires-Dist: commitizen ; extra == 'dev-commit'
Provides-Extra: dev-core
Requires-Dist: disk-numpy-array[dev-commit] ; extra == 'dev-core'
Provides-Extra: dev-doc
Requires-Dist: sphinx ; extra == 'dev-doc'
Requires-Dist: sphinx-autobuild ; extra == 'dev-doc'
Requires-Dist: sphinx-book-theme ; extra == 'dev-doc'
Requires-Dist: sphinx-autoapi ; extra == 'dev-doc'
Requires-Dist: myst-parser ; extra == 'dev-doc'
Requires-Dist: sphinx-design ; extra == 'dev-doc'
Provides-Extra: dev-test
Requires-Dist: tox ; extra == 'dev-test'
Requires-Dist: pytest ; extra == 'dev-test'
Requires-Dist: pytest-cov ; extra == 'dev-test'
